zipcode_in/__init__.py
zipcode_in/__main__.py
zipcode_in/cli_input.py
zipcode_in/test.py
zipcode_in/zipcode.py
zipcode_in/zips.json
zipcode_in/__pycache__/__init__.cpython-38.pyc
zipcode_in/__pycache__/__main__.cpython-38.pyc
zipcode_in/__pycache__/cli_input.cpython-38.pyc
zipcode_in/__pycache__/zipcode.cpython-38.pyc
zipcodes_in-0.2.0.dist-info/LICENSE
zipcodes_in-0.2.0.dist-info/METADATA
zipcodes_in-0.2.0.dist-info/WHEEL
zipcodes_in-0.2.0.dist-info/entry_points.txt
zipcodes_in-0.2.0.dist-info/top_level.txt
zipcodes_in-0.2.0.dist-info/RECORD
