Metadata-Version: 2.1
Name: zipcodes-in
Version: 0.2.0
Summary: Indian Zip Codes
Home-page: https://github.com/arpitfalcon/zipcodes-in
Author: Arpit
Author-email: arpitfalcon1@gmail.com
License: UNKNOWN
Keywords: zipcode zip code india in state validate filter find query
Platform: UNKNOWN
Classifier: Programming Language :: Python :: 3
Classifier: License :: OSI Approved :: MIT License
Classifier: Operating System :: OS Independent
Requires-Python: >=3.6
License-File: LICENSE
